cnmf/__init__.py
cnmf/cnmf.py
cnmf/preprocess.py
cnmf/version.py
cnmf-1.7.0.dist-info/LICENSE
cnmf-1.7.0.dist-info/METADATA
cnmf-1.7.0.dist-info/WHEEL
cnmf-1.7.0.dist-info/entry_points.txt
cnmf-1.7.0.dist-info/top_level.txt
cnmf-1.7.0.dist-info/RECORD
