Metadata-Version: 2.2
Name: cnmf
Version: 1.7.0
Summary: Consensus NMF for scRNA-Seq data
Home-page: https://github.com/dylkot/cNMF
Author: Dylan Kotliar
Author-email: dylkot@gmail.com
Project-URL: Bug Tracker, https://github.com/dylkot/cNMF/issues
Classifier: Programming Language :: Python :: 3
Classifier: License :: OSI Approved :: MIT License
Classifier: Operating System :: OS Independent
License-File: LICENSE
Requires-Dist: scikit-learn>=1.0
Requires-Dist: anndata>=0.9
Requires-Dist: scanpy
Requires-Dist: pandas
Requires-Dist: numpy
Requires-Dist: matplotlib
Requires-Dist: palettable
Requires-Dist: scipy
Requires-Dist: pyyaml
Dynamic: author
Dynamic: author-email
Dynamic: classifier
Dynamic: description
Dynamic: description-content-type
Dynamic: home-page
Dynamic: project-url
Dynamic: requires-dist
Dynamic: summary
